pertpy/__init__.py
pertpy/_doc.py
pertpy/_logger.py
pertpy/_types.py
pertpy/py.typed
pertpy/data/__init__.py
pertpy/data/_dataloader.py
pertpy/data/_datasets.py
pertpy/metadata/__init__.py
pertpy/metadata/_cell_line.py
pertpy/metadata/_compound.py
pertpy/metadata/_drug.py
pertpy/metadata/_look_up.py
pertpy/metadata/_metadata.py
pertpy/metadata/_moa.py
pertpy/plot/__init__.py
pertpy/preprocessing/__init__.py
pertpy/preprocessing/_guide_rna.py
pertpy/preprocessing/_guide_rna_mixture.py
pertpy/tools/__init__.py
pertpy/tools/_augur.py
pertpy/tools/_cinemaot.py
pertpy/tools/_dialogue.py
pertpy/tools/_enrichment.py
pertpy/tools/_milo.py
pertpy/tools/_mixscape.py
pertpy/tools/core.py
pertpy/tools/decoupler_LICENSE
pertpy/tools/transferlearning_MMD_LICENSE
pertpy/tools/_coda/__init__.py
pertpy/tools/_coda/_base_coda.py
pertpy/tools/_coda/_sccoda.py
pertpy/tools/_coda/_tasccoda.py
pertpy/tools/_differential_gene_expression/__init__.py
pertpy/tools/_differential_gene_expression/_base.py
pertpy/tools/_differential_gene_expression/_checks.py
pertpy/tools/_differential_gene_expression/_edger.py
pertpy/tools/_differential_gene_expression/_pydeseq2.py
pertpy/tools/_differential_gene_expression/_simple_tests.py
pertpy/tools/_differential_gene_expression/_statsmodels.py
pertpy/tools/_distances/__init__.py
pertpy/tools/_distances/_distance_tests.py
pertpy/tools/_distances/_distances.py
pertpy/tools/_perturbation_space/__init__.py
pertpy/tools/_perturbation_space/_clustering.py
pertpy/tools/_perturbation_space/_comparison.py
pertpy/tools/_perturbation_space/_discriminator_classifiers.py
pertpy/tools/_perturbation_space/_metrics.py
pertpy/tools/_perturbation_space/_perturbation_space.py
pertpy/tools/_perturbation_space/_simple.py
pertpy/tools/_scgen/__init__.py
pertpy/tools/_scgen/_base_components.py
pertpy/tools/_scgen/_scgen.py
pertpy/tools/_scgen/_scgenvae.py
pertpy/tools/_scgen/_utils.py
pertpy-1.0.4.dist-info/METADATA
pertpy-1.0.4.dist-info/WHEEL
pertpy-1.0.4.dist-info/licenses/LICENSE
pertpy-1.0.4.dist-info/RECORD
