Metadata-Version: 2.4
Name: pertpy
Version: 1.0.4
Summary: Perturbation Analysis in the scverse ecosystem.
Project-URL: Documentation, https://pertpy.readthedocs.io
Project-URL: Source, https://github.com/scverse/pertpy
Project-URL: Home-page, https://github.com/scverse/pertpy
Author: Lukas Heumos, Lilly May, Stefan Peidli, Johannes Ostner, Gregor Sturm, Emma Dann, Yuge Ji, Xinyue Zhang, Xichen Wu, Tessa Green, Antonia Schumacher
Maintainer-email: Lukas Heumos <lukas.heumos@posteo.net>
License: MIT License
License-File: LICENSE
Classifier: Development Status :: 5 - Production/Stable
Classifier: Environment :: Console
Classifier: Framework :: Jupyter
Classifier: Intended Audience :: Developers
Classifier: Intended Audience :: Science/Research
Classifier: License :: OSI Approved :: Apache Software License
Classifier: Natural Language :: English
Classifier: Operating System :: MacOS :: MacOS X
Classifier: Operating System :: POSIX :: Linux
Classifier: Programming Language :: Python :: 3
Classifier: Programming Language :: Python :: 3.12
Classifier: Programming Language :: Python :: 3.13
Classifier: Topic :: Scientific/Engineering :: Bio-Informatics
Classifier: Topic :: Scientific/Engineering :: Visualization
Requires-Python: <3.14,>=3.12
Requires-Dist: adjusttext
Requires-Dist: arviz
Requires-Dist: blitzgsea
Requires-Dist: fast-array-utils[accel,sparse]
Requires-Dist: filelock
Requires-Dist: flax
Requires-Dist: funsor
Requires-Dist: mudata
Requires-Dist: numpyro
Requires-Dist: openpyxl
Requires-Dist: ott-jax
Requires-Dist: pubchempy
Requires-Dist: pyarrow
Requires-Dist: requests
Requires-Dist: rich
Requires-Dist: scanpy
Requires-Dist: scikit-learn>=1.4
Requires-Dist: scikit-misc
Requires-Dist: sparsecca
Provides-Extra: all
Requires-Dist: ete4; extra == 'all'
Requires-Dist: formulaic; extra == 'all'
Requires-Dist: formulaic-contrasts>=0.2.0; extra == 'all'
Requires-Dist: pydeseq2>=v0.5.0; extra == 'all'
Requires-Dist: pyqt6; extra == 'all'
Requires-Dist: scvi-tools[jax]; extra == 'all'
Requires-Dist: toytree>=3.0; extra == 'all'
Provides-Extra: de
Requires-Dist: formulaic; extra == 'de'
Requires-Dist: formulaic-contrasts>=0.2.0; extra == 'de'
Requires-Dist: pydeseq2>=v0.5.0; extra == 'de'
Provides-Extra: dev
Requires-Dist: pre-commit; extra == 'dev'
Provides-Extra: doc
Requires-Dist: docutils>=0.8; extra == 'doc'
Requires-Dist: ipykernel; extra == 'doc'
Requires-Dist: ipython; extra == 'doc'
Requires-Dist: myst-nb; extra == 'doc'
Requires-Dist: nbsphinx; extra == 'doc'
Requires-Dist: nbsphinx-link; extra == 'doc'
Requires-Dist: pygments; extra == 'doc'
Requires-Dist: scanpydoc; extra == 'doc'
Requires-Dist: sphinx-autodoc-typehints; extra == 'doc'
Requires-Dist: sphinx-automodapi; extra == 'doc'
Requires-Dist: sphinx-book-theme; extra == 'doc'
Requires-Dist: sphinx-copybutton; extra == 'doc'
Requires-Dist: sphinx-design; extra == 'doc'
Requires-Dist: sphinx-gallery; extra == 'doc'
Requires-Dist: sphinx-issues; extra == 'doc'
Requires-Dist: sphinx-last-updated-by-git; extra == 'doc'
Requires-Dist: sphinx-remove-toctrees; extra == 'doc'
Requires-Dist: sphinx-tabs; extra == 'doc'
Requires-Dist: sphinx>=8.1; extra == 'doc'
Requires-Dist: sphinxcontrib-bibtex>=1.0.0; extra == 'doc'
Requires-Dist: sphinxext-opengraph; extra == 'doc'
Provides-Extra: milo-edger
Requires-Dist: rpy2; extra == 'milo-edger'
Provides-Extra: scgen
Requires-Dist: scvi-tools[jax]; extra == 'scgen'
Provides-Extra: tcoda
Requires-Dist: ete4; extra == 'tcoda'
Requires-Dist: pyqt6; extra == 'tcoda'
Requires-Dist: toytree>=3.0; extra == 'tcoda'
Provides-Extra: test
Requires-Dist: coverage; extra == 'test'
Requires-Dist: leidenalg; extra == 'test'
Requires-Dist: pytest; extra == 'test'
